pwnedapi/Password.py
pwnedapi/__init__.py
pwnedapi/__main__.py
pwnedapi/__version__.py
pwnedapi/utils.py
pwnedapi/exceptions/PasswordException.py
pwnedapi/exceptions/RequestException.py
pwnedapi/exceptions/__init__.py
pwnedapi-1.0.2.dist-info/LICENSE
pwnedapi-1.0.2.dist-info/METADATA
pwnedapi-1.0.2.dist-info/WHEEL
pwnedapi-1.0.2.dist-info/entry_points.txt
pwnedapi-1.0.2.dist-info/top_level.txt
pwnedapi-1.0.2.dist-info/RECORD
