Metadata-Version: 2.1
Name: pwnedapi
Version: 1.0.2
Summary: Library for easily interfacing with Have I Been Pwned API v2.
Home-page: https://github.com/nikoheikkila/pwnedapi
Author: Niko Heikkilä
Author-email: yo@nikoheikkila.fi
License: MIT
Platform: UNKNOWN
Classifier: License :: OSI Approved :: MIT License
Classifier: Programming Language :: Python
Classifier: Programming Language :: Python :: 3
Classifier: Programming Language :: Python :: 3.5
Classifier: Programming Language :: Python :: Implementation :: CPython
Classifier: Programming Language :: Python :: Implementation :: PyPy
Requires-Python: >=3.5.0
Requires-Dist: requests
Requires-Dist: tablib
Requires-Dist: click
